lastfm_memories/__init__.py
lastfm_memories/cli.py
lastfm_memories/query.py
last.fm_memories-0.1.1.dist-info/METADATA
last.fm_memories-0.1.1.dist-info/WHEEL
last.fm_memories-0.1.1.dist-info/entry_points.txt
last.fm_memories-0.1.1.dist-info/top_level.txt
last.fm_memories-0.1.1.dist-info/RECORD
