Metadata-Version: 2.1
Name: last.fm-memories
Version: 0.1.1
Summary: Lists music you had listened before from Last.fm (or Libre.fm)
Home-page: https://github.com/dahlia/last.fm-memories
Author: Hong Minhee
Author-email: hong.minhee@gmail.com
License: GPLv3+
Platform: UNKNOWN
Classifier: Development Status :: 3 - Alpha
Classifier: Environment :: Console
Classifier: Intended Audience :: End Users/Desktop
Classifier: License :: OSI Approved :: GNU General Public License v3 or later (GPLv3+)
Classifier: Operating System :: OS Independent
Classifier: Programming Language :: Python :: 3.7
Classifier: Programming Language :: Python :: 3 :: Only
Classifier: Programming Language :: Python :: Implementation :: CPython
Classifier: Topic :: Multimedia :: Sound/Audio
Classifier: Topic :: Utilities
Requires-Python: >=3.7
Requires-Dist: appdirs (~=1.4.3)
Requires-Dist: click (~=7.0)
Requires-Dist: MonthDelta (~=0.9.1)
Requires-Dist: pylast (~=2.4.0)
